disposable-email-checker/__init__.py
disposable-email-checker/blocked_email_domains.py
disposable-email-checker/checker.py
disposable_email_checker/__init__.py
disposable_email_checker/blocked_email_domains.py
disposable_email_checker/checker.py
disposable_email_blocker-1.0.0.dist-info/LICENSE
disposable_email_blocker-1.0.0.dist-info/METADATA
disposable_email_blocker-1.0.0.dist-info/WHEEL
disposable_email_blocker-1.0.0.dist-info/top_level.txt
disposable_email_blocker-1.0.0.dist-info/RECORD
