Metadata-Version: 2.1
Name: disposable-email-blocker
Version: 1.0.0
Summary: A library to check if an email is from a disposable domain
Home-page: https://github.com/openmohit28/disposable-email-checker
Author: Mohit Rawat
Author-email: openmohit28@gmail.com
Classifier: Development Status :: 3 - Alpha
Classifier: Intended Audience :: Developers
Classifier: License :: OSI Approved :: MIT License
Classifier: Operating System :: OS Independent
Classifier: Programming Language :: Python :: 3
Classifier: Programming Language :: Python :: 3.6
Classifier: Programming Language :: Python :: 3.7
Classifier: Programming Language :: Python :: 3.8
Classifier: Programming Language :: Python :: 3.9
Requires-Python: >=3.6
License-File: LICENSE
